vast_admin_mcp/__about__.py
vast_admin_mcp/__init__.py
vast_admin_mcp/__main__.py
vast_admin_mcp/cache.py
vast_admin_mcp/cli.py
vast_admin_mcp/client.py
vast_admin_mcp/command_executor.py
vast_admin_mcp/config.py
vast_admin_mcp/create_functions.py
vast_admin_mcp/data_processors.py
vast_admin_mcp/functions.py
vast_admin_mcp/mcp_server.py
vast_admin_mcp/setup.py
vast_admin_mcp/template_parser.py
vast_admin_mcp/utils.py
vast_admin_mcp/cli/__init__.py
vast_admin_mcp/cli/config_helpers.py
vast_admin_mcp/cli/parsers.py
vast_admin_mcp/mcp_list_cmds_template.yaml
vast_admin_mcp-0.1.8.dist-info/METADATA
vast_admin_mcp-0.1.8.dist-info/WHEEL
vast_admin_mcp-0.1.8.dist-info/entry_points.txt
vast_admin_mcp-0.1.8.dist-info/licenses/LICENSE
vast_admin_mcp-0.1.8.dist-info/RECORD
