Metadata-Version: 2.4
Name: vast-admin-mcp
Version: 0.1.8
Summary: VAST Admin MCP Server - MCP server for VAST Data administration tasks
Project-URL: Documentation, https://github.com/vast-data/vast-admin-mcp#readme
Project-URL: Issues, https://github.com/vast-data/vast-admin-mcp/issues
Project-URL: Source, https://github.com/vast-data/vast-admin-mcp
Project-URL: Repository, https://github.com/vast-data/vast-admin-mcp
Author-email: Haim Marko <haim.marko@vastdata.com>
Maintainer-email: Haim Marko <haim.marko@vastdata.com>
License: Apache License 2.0
License-File: LICENSE
Keywords: management,mcp,storage,vast,vast-data
Classifier: Development Status :: 5 - Production/Stable
Classifier: License :: OSI Approved :: MIT License
Classifier: Operating System :: MacOS
Classifier: Operating System :: POSIX :: Linux
Classifier: Programming Language :: Python
Classifier: Programming Language :: Python :: 3.10
Classifier: Programming Language :: Python :: 3.11
Classifier: Programming Language :: Python :: 3.12
Classifier: Programming Language :: Python :: 3.13
Classifier: Programming Language :: Python :: Implementation :: CPython
Classifier: Programming Language :: Python :: Implementation :: PyPy
Classifier: Topic :: System :: Systems Administration
Classifier: Topic :: Utilities
Requires-Python: >=3.10
Requires-Dist: cryptography>=43.0.0
Requires-Dist: fastmcp>=2.13.0.2
Requires-Dist: keyring>=25.0.0
Requires-Dist: keyrings-alt>=5.0.0
Requires-Dist: matplotlib>=3.9.0
Requires-Dist: numpy>=2.0.0
Requires-Dist: pyyaml>=6.0.2
Requires-Dist: scipy>=1.14.0
Requires-Dist: tabulate>=0.9.0
Requires-Dist: urllib3>=1.6.0
Requires-Dist: vastpy>=0.3.20
Provides-Extra: dev
Requires-Dist: watchdog>=3.0.0; extra == 'dev'
